{
  "project_info": {
    "project_number": "674907137625",
    "firebase_url": "https://stream-chat-internal.firebaseio.com",
    "project_id": "stream-chat-internal",
    "storage_bucket": "stream-chat-internal.appspot.com"
  },
  "client": [
    {
      "client_info": {
        "mobilesdk_app_id": "1:674907137625:android:05257db0ea1f2505d7f348",
        "android_client_info": {
          "package_name": "io.getstream.chat.android.client.sample"
        }
      },
      "oauth_client": [
        {
          "client_id": "674907137625-o5iqvv6dtmljtn069b5djv19ad9a7js0.apps.googleusercontent.com",
          "client_type": 3
        }
      ],
      "api_key": [
        {
          "current_key": "AIzaSyBArS4RH7lUn3xbD-jhzWl5hVWZhliRgY0"
        }
      ],
      "services": {
        "appinvite_service": {
          "other_platform_oauth_client": [
            {
              "client_id": "674907137625-o5iqvv6dtmljtn069b5djv19ad9a7js0.apps.googleusercontent.com",
              "client_type": 3
            },
            {
              "client_id": "674907137625-flarfn9cefu4lermgpbc4b8rm8l15ian.apps.googleusercontent.com",
              "client_type": 2,
              "ios_info": {
                "bundle_id": "io.getstream.flutter"
              }
            }
          ]
        }
      }
    },
    {
      "client_info": {
        "mobilesdk_app_id": "1:674907137625:android:c41e48c4c799aee8d7f348",
        "android_client_info": {
          "package_name": "io.getstream.chat.example"
        }
      },
      "oauth_client": [
        {
          "client_id": "674907137625-o5iqvv6dtmljtn069b5djv19ad9a7js0.apps.googleusercontent.com",
          "client_type": 3
        }
      ],
      "api_key": [
        {
          "current_key": "AIzaSyBArS4RH7lUn3xbD-jhzWl5hVWZhliRgY0"
        }
      ],
      "services": {
        "appinvite_service": {
          "other_platform_oauth_client": [
            {
              "client_id": "674907137625-o5iqvv6dtmljtn069b5djv19ad9a7js0.apps.googleusercontent.com",
              "client_type": 3
            },
            {
              "client_id": "674907137625-flarfn9cefu4lermgpbc4b8rm8l15ian.apps.googleusercontent.com",
              "client_type": 2,
              "ios_info": {
                "bundle_id": "io.getstream.flutter"
              }
            }
          ]
        }
      }
    },
    {
      "client_info": {
        "mobilesdk_app_id": "1:674907137625:android:c36d6f4ab7491192d7f348",
        "android_client_info": {
          "package_name": "io.getstream.chat.ui.sample"
        }
      },
      "oauth_client": [
        {
          "client_id": "674907137625-o5iqvv6dtmljtn069b5djv19ad9a7js0.apps.googleusercontent.com",
          "client_type": 3
        }
      ],
      "api_key": [
        {
          "current_key": "AIzaSyBArS4RH7lUn3xbD-jhzWl5hVWZhliRgY0"
        }
      ],
      "services": {
        "appinvite_service": {
          "other_platform_oauth_client": [
            {
              "client_id": "674907137625-o5iqvv6dtmljtn069b5djv19ad9a7js0.apps.googleusercontent.com",
              "client_type": 3
            },
            {
              "client_id": "674907137625-flarfn9cefu4lermgpbc4b8rm8l15ian.apps.googleusercontent.com",
              "client_type": 2,
              "ios_info": {
                "bundle_id": "io.getstream.flutter"
              }
            }
          ]
        }
      }
    },
    {
      "client_info": {
        "mobilesdk_app_id": "1:674907137625:android:d91b4d966e372431d7f348",
        "android_client_info": {
          "package_name": "io.getstream.chat.ui.sample.debug"
        }
      },
      "oauth_client": [
        {
          "client_id": "674907137625-o5iqvv6dtmljtn069b5djv19ad9a7js0.apps.googleusercontent.com",
          "client_type": 3
        }
      ],
      "api_key": [
        {
          "current_key": "AIzaSyBArS4RH7lUn3xbD-jhzWl5hVWZhliRgY0"
        }
      ],
      "services": {
        "appinvite_service": {
          "other_platform_oauth_client": [
            {
              "client_id": "674907137625-o5iqvv6dtmljtn069b5djv19ad9a7js0.apps.googleusercontent.com",
              "client_type": 3
            },
            {
              "client_id": "674907137625-flarfn9cefu4lermgpbc4b8rm8l15ian.apps.googleusercontent.com",
              "client_type": 2,
              "ios_info": {
                "bundle_id": "io.getstream.flutter"
              }
            }
          ]
        }
      }
    },
    {
      "client_info": {
        "mobilesdk_app_id": "1:674907137625:android:ff6593c705df1c43d7f348",
        "android_client_info": {
          "package_name": "io.getstream.chat.sdk"
        }
      },
      "oauth_client": [
        {
          "client_id": "674907137625-khntpmmm3s1756v4jugnhcifgjlqrmd0.apps.googleusercontent.com",
          "client_type": 1,
          "android_info": {
            "package_name": "io.getstream.chat.sdk",
            "certificate_hash": "38f7d663a2ed58ae8990d365c41bd82df62185dc"
          }
        },
        {
          "client_id": "674907137625-o5iqvv6dtmljtn069b5djv19ad9a7js0.apps.googleusercontent.com",
          "client_type": 3
        }
      ],
      "api_key": [
        {
          "current_key": "AIzaSyBArS4RH7lUn3xbD-jhzWl5hVWZhliRgY0"
        }
      ],
      "services": {
        "appinvite_service": {
          "other_platform_oauth_client": [
            {
              "client_id": "674907137625-o5iqvv6dtmljtn069b5djv19ad9a7js0.apps.googleusercontent.com",
              "client_type": 3
            },
            {
              "client_id": "674907137625-flarfn9cefu4lermgpbc4b8rm8l15ian.apps.googleusercontent.com",
              "client_type": 2,
              "ios_info": {
                "bundle_id": "io.getstream.flutter"
              }
            }
          ]
        }
      }
    }
  ],
  "configuration_version": "1"
}